{
   "page":1,
   "results":[
      {
         "backdrop_path":"/4g5gK5eGWZg8swIZl6eX2AoJp8S.jpg",
         "first_air_date":"2003-10-21",
         "genre_ids":[
            18
         ],
         "id":11250,
         "name":"Pasión de gavilanes",
         "origin_country":[
            "CO"
         ],
         "original_language":"es",
         "original_name":"Pasión de gavilanes",
         "overview":"Los hermanos Reyes buscan vengar la muerte de su hermana, lo que les lleva a instalarse como trabajadores en la mansión de la familia Elizondo. El profundo odio comienza a cambiar cuando los hermanos Reyes se integran en la vida de la familia. Con lo que no cuenta Juan es con que su vida y las de sus dos hermanos se cruzará con la de las tres hermanas Elizondo, corriendo el riesgo de caer presos de su propia venganza...",
         "popularity":5604.281,
         "poster_path":"/91UV7pNcDPhIzJl7EuK36sK5vRG.jpg",
         "vote_average":7.7,
         "vote_count":1697
      },
      {
         "backdrop_path":null,
         "first_air_date":"1972-09-04",
         "genre_ids":[
            
         ],
         "id":2051,
         "name":"The Price Is Right",
         "origin_country":[
            "US"
         ],
         "original_language":"en",
         "original_name":"The Price Is Right",
         "overview":"",
         "popularity":1791.434,
         "poster_path":"/6m4uYFAJwkanZXd0n0HUQ0lYHLl.jpg",
         "vote_average":6.2,
         "vote_count":50
      },
      {
         "backdrop_path":"/yfXSvNfF43S0cxpxCEKaU17yZ64.jpg",
         "first_air_date":"1983-09-19",
         "genre_ids":[
            10751
         ],
         "id":2778,
         "name":"Wheel of Fortune",
         "origin_country":[
            "US"
         ],
         "original_language":"en",
         "original_name":"Wheel of Fortune",
         "overview":"",
         "popularity":1439.523,
         "poster_path":"/2fvAIyVfFHQdhJ7OsJWuMlF7836.jpg",
         "vote_average":6.9,
         "vote_count":45
      },
      {
         "backdrop_path":"/vhEtBjbxLMlPTPCS6TGk0WLo9C8.jpg",
         "first_air_date":"2021-09-09",
         "genre_ids":[
            10764
         ],
         "id":132712,
         "name":"Secret Story: La casa de los secretos",
         "origin_country":[
            "ES"
         ],
         "original_language":"es",
         "original_name":"Secret Story: La casa de los secretos",
         "overview":"Los famosos participantes tendrán que mantener su secreto a salvo, mientras intentan descubrir el de sus compañeros. Los espectadores se convertirán en auténticos investigadores y serán testigos de las estrategias de los concursantes. Además, la audiencia será testigo de su convivencia 24 horas y decidirá el devenir del concurso.",
         "popularity":1412.276,
         "poster_path":"/rucYOgpymV2gAvyJUVK1awLTOcH.jpg",
         "vote_average":3,
         "vote_count":2
      },
      {
         "backdrop_path":"/l6zdjUDOaklBWfxqa7AtbLr2EnA.jpg",
         "first_air_date":"2021-12-13",
         "genre_ids":[
            10751,
            35,
            18
         ],
         "id":135753,
         "name":"사랑의 꽈배기",
         "origin_country":[
            "KR"
         ],
         "original_language":"ko",
         "original_name":"사랑의 꽈배기",
         "overview":"",
         "popularity":1371.044,
         "poster_path":"/GM1yyjtc1wcmG3RLAERRmSFm1e.jpg",
         "vote_average":4.5,
         "vote_count":2
      },
      {
         "backdrop_path":"/s0L56Zv3NVH1kZTrLfTQ2kwvQeD.jpg",
         "first_air_date":"2022-01-24",
         "genre_ids":[
            18
         ],
         "id":125030,
         "name":"The Broken Marriage Vow",
         "origin_country":[
            "PH"
         ],
         "original_language":"tl",
         "original_name":"The Broken Marriage Vow",
         "overview":"",
         "popularity":1370.726,
         "poster_path":"/gBJIKWkI90L57ky6EUzQGE6wWpJ.jpg",
         "vote_average":5.5,
         "vote_count":2
      },
      {
         "backdrop_path":"/q9o7VEHX0O9oixdIa6uT0v5lu3S.jpg",
         "first_air_date":"2022-01-28",
         "genre_ids":[
            18
         ],
         "id":156568,
         "name":"人世间",
         "origin_country":[
            "CN"
         ],
         "original_language":"zh",
         "original_name":"人世间",
         "overview":"",
         "popularity":1317.034,
         "poster_path":"/u5LOe5BMtNPticKT9fAzTkxSlst.jpg",
         "vote_average":6.7,
         "vote_count":3
      },
      {
         "backdrop_path":"/r8CGqB8IJNbA1IruHWquS7YttNB.jpg",
         "first_air_date":"1995-10-23",
         "genre_ids":[
            10766
         ],
         "id":966,
         "name":"Hollyoaks",
         "origin_country":[
            "GB"
         ],
         "original_language":"en",
         "original_name":"Hollyoaks",
         "overview":"",
         "popularity":1172.588,
         "poster_path":"/bpmLMZP3M1vLujPqHnOTnKVjRJY.jpg",
         "vote_average":5.1,
         "vote_count":37
      },
      {
         "backdrop_path":"/nSpM93RELv7rJBzlWbHzjOJ7Mhi.jpg",
         "first_air_date":"2021-11-08",
         "genre_ids":[
            
         ],
         "id":137007,
         "name":"Tug of Words",
         "origin_country":[
            
         ],
         "original_language":"en",
         "original_name":"Tug of Words",
         "overview":"",
         "popularity":1038.579,
         "poster_path":"/vHLV2e5JcBaw1D17v9ftayf5YsO.jpg",
         "vote_average":1.5,
         "vote_count":2
      },
      {
         "backdrop_path":"/l8WwTX2o16n3MbD6Yz2NNYKOt8i.jpg",
         "first_air_date":"2019-09-09",
         "genre_ids":[
            10764
         ],
         "id":93364,
         "name":"Judge Jerry",
         "origin_country":[
            "US"
         ],
         "original_language":"en",
         "original_name":"Judge Jerry",
         "overview":"",
         "popularity":915.493,
         "poster_path":"/54iJ45FF2m9jNsioGltHypVlvKh.jpg",
         "vote_average":5.3,
         "vote_count":4
      },
      {
         "backdrop_path":"/3vr4dAoT6eluIY16mjROK20QrR4.jpg",
         "first_air_date":"2003-01-26",
         "genre_ids":[
            10767,
            35
         ],
         "id":1489,
         "name":"Jimmy Kimmel Live!",
         "origin_country":[
            "US"
         ],
         "original_language":"en",
         "original_name":"Jimmy Kimmel Live!",
         "overview":"",
         "popularity":733.691,
         "poster_path":"/pUTTBIUO4U5rZjYcZ3Lk51vHr20.jpg",
         "vote_average":5.7,
         "vote_count":97
      },
      {
         "backdrop_path":"/uOPVhgfljgOM1SNz7eXuPHti9oK.jpg",
         "first_air_date":"1988-09-05",
         "genre_ids":[
            10767
         ],
         "id":1900,
         "name":"LIVE with Kelly and Ryan",
         "origin_country":[
            "US"
         ],
         "original_language":"en",
         "original_name":"LIVE with Kelly and Ryan",
         "overview":"",
         "popularity":732.496,
         "poster_path":"/hBkyypWN3EcOzkozatiCm5VeaG.jpg",
         "vote_average":5,
         "vote_count":17
      },
      {
         "backdrop_path":null,
         "first_air_date":"2021-03-29",
         "genre_ids":[
            10763
         ],
         "id":119903,
         "name":"Noovo Le Fil 17",
         "origin_country":[
            "CA"
         ],
         "original_language":"fr",
         "original_name":"Noovo Le Fil 17",
         "overview":"",
         "popularity":686.494,
         "poster_path":"/ppPQS4XAUTguEVKWl4HRye4H7BU.jpg",
         "vote_average":1.3,
         "vote_count":3
      },
      {
         "backdrop_path":"/2748H9LoK2oQd9L7ofze8VjCGhS.jpg",
         "first_air_date":"2020-07-13",
         "genre_ids":[
            18,
            10766
         ],
         "id":116479,
         "name":"Anupama",
         "origin_country":[
            "IN"
         ],
         "original_language":"hi",
         "original_name":"अनुपमा",
         "overview":"Anupama tuvo que sacrificar mucho para convertirse en una esposa, nuera y madre ideales. Después de una amarga comprensión, se propone vivir en sus propios términos.",
         "popularity":677.424,
         "poster_path":"/9R4Qtm01pNh0CzdoIyvHKefe5RL.jpg",
         "vote_average":4.4,
         "vote_count":23
      },
      {
         "backdrop_path":"/vjcuLy14kxgxCaBToAudZWrGQQh.jpg",
         "first_air_date":"2021-01-18",
         "genre_ids":[
            10764
         ],
         "id":117031,
         "name":"People Puzzler",
         "origin_country":[
            
         ],
         "original_language":"en",
         "original_name":"People Puzzler",
         "overview":"",
         "popularity":658.418,
         "poster_path":"/gELQSCY5KKIGQAmOHbcgcRGNlp5.jpg",
         "vote_average":5.5,
         "vote_count":11
      },
      {
         "backdrop_path":null,
         "first_air_date":"2021-03-29",
         "genre_ids":[
            10763
         ],
         "id":122152,
         "name":"Noovo Le Fil Québec",
         "origin_country":[
            "CA"
         ],
         "original_language":"fr",
         "original_name":"Noovo Le Fil Québec",
         "overview":"",
         "popularity":655.685,
         "poster_path":"/kdpM5Iz37EWi6hRMWZvrQRxTpEF.jpg",
         "vote_average":10,
         "vote_count":1
      },
      {
         "backdrop_path":null,
         "first_air_date":"2021-03-29",
         "genre_ids":[
            10763
         ],
         "id":122151,
         "name":"Noovo Le Fil 22",
         "origin_country":[
            "CA"
         ],
         "original_language":"fr",
         "original_name":"Noovo Le Fil 22",
         "overview":"",
         "popularity":655.569,
         "poster_path":"/x70JHANtSvS8IiTadaDrXY1PQBB.jpg",
         "vote_average":1,
         "vote_count":1
      },
      {
         "backdrop_path":"/wAAuhiwWqH42Xc3UZjDBUlGvk63.jpg",
         "first_air_date":"2013-09-23",
         "genre_ids":[
            18,
            80,
            9648
         ],
         "id":46952,
         "name":"The Blacklist",
         "origin_country":[
            "US"
         ],
         "original_language":"en",
         "original_name":"The Blacklist",
         "overview":"El criminal más buscado del mundo, Thomas Raymond Reddington, se entrega misteriosamente y se ofrece a delatar a todos los que alguna vez han colaborado con él. Su única condición: sólo colaborará con Elisabeth King, una nueva agente del FBI, con quien parece tener alguna conexión que ella desconoce.",
         "popularity":644.711,
         "poster_path":"/2jDYeTaDSIYnVOS4BD3d17JBkfP.jpg",
         "vote_average":7.5,
         "vote_count":2277
      },
      {
         "backdrop_path":"/bX6embf0yknbV6R5NVUwM60FQXG.jpg",
         "first_air_date":"2021-11-22",
         "genre_ids":[
            10766,
            35
         ],
         "id":139009,
         "name":"Quanto Mais Vida, Melhor!",
         "origin_country":[
            "BR"
         ],
         "original_language":"pt",
         "original_name":"Quanto Mais Vida, Melhor!",
         "overview":"",
         "popularity":625.822,
         "poster_path":"/ydtfMZMu04L5noElS35BespN8rV.jpg",
         "vote_average":4.5,
         "vote_count":3
      },
      {
         "backdrop_path":"/8lBlBItnehgOAwFt0ezxlXuWeIO.jpg",
         "first_air_date":"2021-11-08",
         "genre_ids":[
            10766,
            18
         ],
         "id":132375,
         "name":"Vidas Ajenas",
         "origin_country":[
            "BR"
         ],
         "original_language":"pt",
         "original_name":"Um Lugar ao Sol",
         "overview":"Christian y Renato son gemelos idénticos de vidas opuestas: Christian creció en un orfanato y lucha en un subempleo para sobrevivir. Renato, por otro lado, fue adoptado por una familia adinerada y tenía todo lo que el dinero podía comprar. Cuando se reencuentran, como adultos, ocurre una tragedia: Renato es asesinado e identificado como Christian quien, a su vez, toma el lugar de su hermano. Para eso, sin embargo, necesita dejar atrás su identidad y su gran amor.",
         "popularity":618.88,
         "poster_path":"/63qlVcvlVzOvMaFO8tFA2VG64Yc.jpg",
         "vote_average":5.6,
         "vote_count":7
      }
   ],
   "total_pages":14,
   "total_results":271
}
